pypeto/__init__.py
pypeto/__main__.py
pypeto/cad_epics.py
pypeto/cad_pvaccess.py
pypeto/detachable_tabs.py
pypeto/pypet.py
pypeto/pypet_203.py
pypeto/pypet_204.py
pypeto/test.py
pypeto-3.1.0.dist-info/METADATA
pypeto-3.1.0.dist-info/WHEEL
pypeto-3.1.0.dist-info/licenses/LICENSE
pypeto-3.1.0.dist-info/RECORD
