Metadata-Version: 2.4
Name: pypeto
Version: 3.1.0
Summary: Tabular control of process variables for EPICS or LiteServer devices
Project-URL: Homepage, https://github.com/ASukhanov/pypeto
Project-URL: Bug Tracker, https://github.com/ASukhanov/pypeto/issues
Author-email: Andrei Sukhanov <cyxandr@gmail.com>
License-File: LICENSE
Classifier: License :: OSI Approved :: MIT License
Classifier: Operating System :: OS Independent
Classifier: Programming Language :: Python :: 3
Requires-Python: >=3.8
Requires-Dist: caproto
Requires-Dist: liteaccess
Requires-Dist: qtpy
